odoo/addons/account_move_transactionid_import/README.rst
odoo/addons/account_move_transactionid_import/__init__.py
odoo/addons/account_move_transactionid_import/__manifest__.py
odoo/addons/account_move_transactionid_import/data/completion_rule_data.xml
odoo/addons/account_move_transactionid_import/i18n/account_move_transactionid_import.pot
odoo/addons/account_move_transactionid_import/i18n/de.po
odoo/addons/account_move_transactionid_import/i18n/es.po
odoo/addons/account_move_transactionid_import/i18n/fr.po
odoo/addons/account_move_transactionid_import/i18n/hr_HR.po
odoo/addons/account_move_transactionid_import/i18n/it.po
odoo/addons/account_move_transactionid_import/i18n/pt_BR.po
odoo/addons/account_move_transactionid_import/i18n/sl.po
odoo/addons/account_move_transactionid_import/models/__init__.py
odoo/addons/account_move_transactionid_import/models/account_journal.py
odoo/addons/account_move_transactionid_import/models/account_move.py
odoo/addons/account_move_transactionid_import/parser/__init__.py
odoo/addons/account_move_transactionid_import/parser/transactionid_file_parser.py
odoo/addons/account_move_transactionid_import/readme/CONTRIBUTORS.rst
odoo/addons/account_move_transactionid_import/readme/DESCRIPTION.rst
odoo/addons/account_move_transactionid_import/static/description/icon.png
odoo/addons/account_move_transactionid_import/static/description/index.html
odoo/addons/account_move_transactionid_import/tests/__init__.py
odoo/addons/account_move_transactionid_import/tests/test_completion_transaction_id.py
odoo/addons/account_move_transactionid_import/tests/test_transactionid_import.py
odoo/addons/account_move_transactionid_import/tests/data/completion_rule_data.xml
odoo/addons/account_move_transactionid_import/tests/data/statement.csv
odoo/addons/account_move_transactionid_import/tests/data/statement.xls
odoo12_addon_account_move_transactionid_import-12.0.3.0.0.dist-info/METADATA
odoo12_addon_account_move_transactionid_import-12.0.3.0.0.dist-info/WHEEL
odoo12_addon_account_move_transactionid_import-12.0.3.0.0.dist-info/top_level.txt
odoo12_addon_account_move_transactionid_import-12.0.3.0.0.dist-info/RECORD
